<?xml version="1.0" encoding="utf-8"?>
<TextureAtlas imagePath="when se petatean al bief coño.png">
	<!-- Created with Adobe Animate version 22.0.2.168 -->
	<!-- http://www.adobe.com/products/animate.html -->
	<SubTexture name="bf toy muerte0000" x="27" y="27" width="424" height="545" frameX="-474" frameY="-341" frameWidth="1159" frameHeight="939"/>
	<SubTexture name="bf toy muerte0001" x="27" y="27" width="424" height="545" frameX="-474" frameY="-341" frameWidth="1159" frameHeight="939"/>
	<SubTexture name="bf toy muerte0002" x="478" y="27" width="432" height="538" frameX="-474" frameY="-348" frameWidth="1159" frameHeight="939"/>
	<SubTexture name="bf toy muerte0003" x="478" y="27" width="432" height="538" frameX="-474" frameY="-348" frameWidth="1159" frameHeight="939"/>
	<SubTexture name="bf toy muerte0004" x="937" y="27" width="432" height="538" frameX="-474" frameY="-348" frameWidth="1159" frameHeight="939"/>
	<SubTexture name="bf toy muerte0005" x="937" y="27" width="432" height="538" frameX="-474" frameY="-348" frameWidth="1159" frameHeight="939"/>
	<SubTexture name="bf toy muerte0006" x="1396" y="27" width="435" height="538" frameX="-474" frameY="-348" frameWidth="1159" frameHeight="939"/>
	<SubTexture name="bf toy muerte0007" x="1396" y="27" width="435" height="538" frameX="-474" frameY="-348" frameWidth="1159" frameHeight="939"/>
	<SubTexture name="bf toy muerte0008" x="1858" y="27" width="439" height="538" frameX="-474" frameY="-348" frameWidth="1159" frameHeight="939"/>
	<SubTexture name="bf toy muerte0009" x="2324" y="27" width="448" height="538" frameX="-474" frameY="-348" frameWidth="1159" frameHeight="939"/>
	<SubTexture name="bf toy muerte0010" x="2799" y="27" width="448" height="538" frameX="-474" frameY="-348" frameWidth="1159" frameHeight="939"/>
	<SubTexture name="bf toy muerte0011" x="3274" y="27" width="465" height="538" frameX="-474" frameY="-348" frameWidth="1159" frameHeight="939"/>
	<SubTexture name="bf toy muerte0012" x="3766" y="27" width="531" height="538" frameX="-474" frameY="-348" frameWidth="1159" frameHeight="939"/>
	<SubTexture name="bf toy muerte0013" x="3766" y="27" width="531" height="538" frameX="-474" frameY="-348" frameWidth="1159" frameHeight="939"/>
	<SubTexture name="bf toy muerte0014" x="4324" y="27" width="532" height="538" frameX="-474" frameY="-348" frameWidth="1159" frameHeight="939"/>
	<SubTexture name="bf toy muerte0015" x="4324" y="27" width="532" height="538" frameX="-474" frameY="-348" frameWidth="1159" frameHeight="939"/>
	<SubTexture name="bf toy muerte0016" x="4883" y="27" width="531" height="538" frameX="-474" frameY="-348" frameWidth="1159" frameHeight="939"/>
	<SubTexture name="bf toy muerte0017" x="4883" y="27" width="531" height="538" frameX="-474" frameY="-348" frameWidth="1159" frameHeight="939"/>
	<SubTexture name="bf toy muerte0018" x="5441" y="27" width="531" height="538" frameX="-474" frameY="-348" frameWidth="1159" frameHeight="939"/>
	<SubTexture name="bf toy muerte0019" x="5441" y="27" width="531" height="538" frameX="-474" frameY="-348" frameWidth="1159" frameHeight="939"/>
	<SubTexture name="bf toy muerte0020" x="4883" y="27" width="531" height="538" frameX="-474" frameY="-348" frameWidth="1159" frameHeight="939"/>
	<SubTexture name="bf toy muerte0021" x="4883" y="27" width="531" height="538" frameX="-474" frameY="-348" frameWidth="1159" frameHeight="939"/>
	<SubTexture name="bf toy muerte0022" x="5441" y="27" width="531" height="538" frameX="-474" frameY="-348" frameWidth="1159" frameHeight="939"/>
	<SubTexture name="bf toy muerte0023" x="5441" y="27" width="531" height="538" frameX="-474" frameY="-348" frameWidth="1159" frameHeight="939"/>
	<SubTexture name="bf toy muerte0024" x="4883" y="27" width="531" height="538" frameX="-474" frameY="-348" frameWidth="1159" frameHeight="939"/>
	<SubTexture name="bf toy muerte0025" x="4883" y="27" width="531" height="538" frameX="-474" frameY="-348" frameWidth="1159" frameHeight="939"/>
	<SubTexture name="bf toy muerte0026" x="5441" y="27" width="531" height="538" frameX="-474" frameY="-348" frameWidth="1159" frameHeight="939"/>
	<SubTexture name="bf toy muerte0027" x="5441" y="27" width="531" height="538" frameX="-474" frameY="-348" frameWidth="1159" frameHeight="939"/>
	<SubTexture name="bf toy muerte0028" x="4883" y="27" width="531" height="538" frameX="-474" frameY="-348" frameWidth="1159" frameHeight="939"/>
	<SubTexture name="bf toy muerte0029" x="4883" y="27" width="531" height="538" frameX="-474" frameY="-348" frameWidth="1159" frameHeight="939"/>
	<SubTexture name="bf toy muerte0030" x="5441" y="27" width="531" height="538" frameX="-474" frameY="-348" frameWidth="1159" frameHeight="939"/>
	<SubTexture name="bf toy muerte0031" x="5441" y="27" width="531" height="538" frameX="-474" frameY="-348" frameWidth="1159" frameHeight="939"/>
	<SubTexture name="bf toy muerte0032" x="4883" y="27" width="531" height="538" frameX="-474" frameY="-348" frameWidth="1159" frameHeight="939"/>
	<SubTexture name="bf toy muerte0033" x="4883" y="27" width="531" height="538" frameX="-474" frameY="-348" frameWidth="1159" frameHeight="939"/>
	<SubTexture name="bf toy muerte0034" x="5441" y="27" width="531" height="538" frameX="-474" frameY="-348" frameWidth="1159" frameHeight="939"/>
	<SubTexture name="bf toy muerte0035" x="5441" y="27" width="531" height="538" frameX="-474" frameY="-348" frameWidth="1159" frameHeight="939"/>
	<SubTexture name="bf toy muerte0036" x="4883" y="27" width="531" height="538" frameX="-474" frameY="-348" frameWidth="1159" frameHeight="939"/>
	<SubTexture name="bf toy muerte0037" x="5999" y="27" width="1005" height="670" frameX="0" frameY="-269" frameWidth="1159" frameHeight="939"/>
	<SubTexture name="bf toy muerte0038" x="7031" y="27" width="1005" height="670" frameX="0" frameY="-269" frameWidth="1159" frameHeight="939"/>
	<SubTexture name="bf toy muerte0039" x="27" y="724" width="1005" height="670" frameX="0" frameY="-269" frameWidth="1159" frameHeight="939"/>
	<SubTexture name="bf toy muerte0040" x="1059" y="724" width="1005" height="670" frameX="0" frameY="-269" frameWidth="1159" frameHeight="939"/>
	<SubTexture name="bf toy muerte0041" x="1059" y="724" width="1005" height="670" frameX="0" frameY="-269" frameWidth="1159" frameHeight="939"/>
	<SubTexture name="bf toy muerte0042" x="27" y="724" width="1005" height="670" frameX="0" frameY="-269" frameWidth="1159" frameHeight="939"/>
	<SubTexture name="bf toy muerte0043" x="2091" y="724" width="1005" height="670" frameX="0" frameY="-269" frameWidth="1159" frameHeight="939"/>
	<SubTexture name="bf toy muerte0044" x="3123" y="724" width="1005" height="670" frameX="0" frameY="-269" frameWidth="1159" frameHeight="939"/>
	<SubTexture name="bf toy muerte0045" x="4155" y="724" width="1005" height="670" frameX="0" frameY="-269" frameWidth="1159" frameHeight="939"/>
	<SubTexture name="bf toy muerte0046" x="5187" y="724" width="1005" height="670" frameX="0" frameY="-269" frameWidth="1159" frameHeight="939"/>
	<SubTexture name="bf toy muerte0047" x="6219" y="724" width="1005" height="670" frameX="0" frameY="-269" frameWidth="1159" frameHeight="939"/>
	<SubTexture name="bf toy muerte0048" x="27" y="1421" width="1005" height="670" frameX="0" frameY="-269" frameWidth="1159" frameHeight="939"/>
	<SubTexture name="bf toy muerte0049" x="1059" y="1421" width="531" height="538" frameX="-474" frameY="-348" frameWidth="1159" frameHeight="939"/>
	<SubTexture name="bf toy muerte0050" x="1617" y="1421" width="531" height="538" frameX="-474" frameY="-348" frameWidth="1159" frameHeight="939"/>
	<SubTexture name="bf toy muerte0051" x="2175" y="1421" width="531" height="538" frameX="-474" frameY="-348" frameWidth="1159" frameHeight="939"/>
	<SubTexture name="bf toy muerte0052" x="2175" y="1421" width="531" height="538" frameX="-474" frameY="-348" frameWidth="1159" frameHeight="939"/>
	<SubTexture name="bf toy muerte0053" x="2733" y="1421" width="531" height="538" frameX="-474" frameY="-348" frameWidth="1159" frameHeight="939"/>
	<SubTexture name="bf toy muerte0054" x="2733" y="1421" width="531" height="538" frameX="-474" frameY="-348" frameWidth="1159" frameHeight="939"/>
	<SubTexture name="bf toy muerte0055" x="2733" y="1421" width="531" height="538" frameX="-474" frameY="-348" frameWidth="1159" frameHeight="939"/>
	<SubTexture name="bf toy muerte0056" x="3291" y="1421" width="531" height="538" frameX="-474" frameY="-348" frameWidth="1159" frameHeight="939"/>
	<SubTexture name="bf toy muerte0057" x="3849" y="1421" width="531" height="540" frameX="-474" frameY="-346" frameWidth="1159" frameHeight="939"/>
	<SubTexture name="bf toy muerte0058" x="3849" y="1421" width="531" height="540" frameX="-474" frameY="-346" frameWidth="1159" frameHeight="939"/>
	<SubTexture name="bf toy muerte0059" x="4407" y="1421" width="531" height="540" frameX="-474" frameY="-346" frameWidth="1159" frameHeight="939"/>
	<SubTexture name="bf toy muerte0060" x="4407" y="1421" width="531" height="540" frameX="-474" frameY="-346" frameWidth="1159" frameHeight="939"/>
	<SubTexture name="bf toy muerte0061" x="4965" y="1421" width="531" height="545" frameX="-474" frameY="-336" frameWidth="1159" frameHeight="939"/>
	<SubTexture name="bf toy muerte0062" x="4965" y="1421" width="531" height="545" frameX="-474" frameY="-336" frameWidth="1159" frameHeight="939"/>
	<SubTexture name="bf toy muerte0063" x="4965" y="1421" width="531" height="545" frameX="-474" frameY="-336" frameWidth="1159" frameHeight="939"/>
	<SubTexture name="bf toy muerte0064" x="4965" y="1421" width="531" height="545" frameX="-474" frameY="-336" frameWidth="1159" frameHeight="939"/>
	<SubTexture name="bf toy muerte0065" x="4965" y="1421" width="531" height="545" frameX="-474" frameY="-336" frameWidth="1159" frameHeight="939"/>
	<SubTexture name="bf toy muerte0066" x="4965" y="1421" width="531" height="545" frameX="-474" frameY="-336" frameWidth="1159" frameHeight="939"/>
	<SubTexture name="bf toy muerte0067" x="5523" y="1421" width="531" height="543" frameX="-474" frameY="-338" frameWidth="1159" frameHeight="939"/>
	<SubTexture name="bf toy muerte0068" x="5523" y="1421" width="531" height="543" frameX="-474" frameY="-338" frameWidth="1159" frameHeight="939"/>
	<SubTexture name="bf toy muerte0069" x="6081" y="1421" width="531" height="879" frameX="-474" frameY="-2" frameWidth="1159" frameHeight="939"/>
	<SubTexture name="bf toy muerte0070" x="6081" y="1421" width="531" height="879" frameX="-474" frameY="-2" frameWidth="1159" frameHeight="939"/>
	<SubTexture name="bf toy muerte0071" x="6639" y="1421" width="531" height="174" frameX="-474" frameY="-707" frameWidth="1159" frameHeight="939"/>
	<SubTexture name="bf toy muerte0072" x="6639" y="1421" width="531" height="174" frameX="-474" frameY="-707" frameWidth="1159" frameHeight="939"/>
	<SubTexture name="bf toy muerte0073" x="6639" y="1421" width="531" height="174" frameX="-474" frameY="-707" frameWidth="1159" frameHeight="939"/>
	<SubTexture name="bf toy muerte0074" x="6639" y="1421" width="531" height="174" frameX="-474" frameY="-707" frameWidth="1159" frameHeight="939"/>
	<SubTexture name="bf toy muerte0075" x="6639" y="1421" width="531" height="174" frameX="-474" frameY="-707" frameWidth="1159" frameHeight="939"/>
	<SubTexture name="bf toy muerte0076" x="6639" y="1421" width="531" height="174" frameX="-474" frameY="-707" frameWidth="1159" frameHeight="939"/>
	<SubTexture name="bf toy muerte0077" x="6639" y="1421" width="531" height="174" frameX="-474" frameY="-707" frameWidth="1159" frameHeight="939"/>
	<SubTexture name="bf toy muerte0078" x="6639" y="1421" width="531" height="174" frameX="-474" frameY="-707" frameWidth="1159" frameHeight="939"/>
	<SubTexture name="bf toy muerte0079" x="6639" y="1421" width="531" height="174" frameX="-474" frameY="-707" frameWidth="1159" frameHeight="939"/>
	<SubTexture name="bf toy muerte0080" x="6639" y="1421" width="531" height="174" frameX="-474" frameY="-707" frameWidth="1159" frameHeight="939"/>
	<SubTexture name="bf toy muerte0081" x="6639" y="1421" width="531" height="174" frameX="-474" frameY="-707" frameWidth="1159" frameHeight="939"/>
	<SubTexture name="bf toy muerte0082" x="6639" y="1421" width="531" height="174" frameX="-474" frameY="-707" frameWidth="1159" frameHeight="939"/>
	<SubTexture name="bf toy muerte0083" x="6639" y="1421" width="531" height="174" frameX="-474" frameY="-707" frameWidth="1159" frameHeight="939"/>
	<SubTexture name="bf toy muerte0084" x="6639" y="1421" width="531" height="174" frameX="-474" frameY="-707" frameWidth="1159" frameHeight="939"/>
	<SubTexture name="bf toy muerte0085" x="6639" y="1421" width="531" height="174" frameX="-474" frameY="-707" frameWidth="1159" frameHeight="939"/>
	<SubTexture name="bf toy muerte0086" x="6639" y="1421" width="531" height="174" frameX="-474" frameY="-707" frameWidth="1159" frameHeight="939"/>
	<SubTexture name="bf toy muerte0087" x="6639" y="1421" width="531" height="174" frameX="-474" frameY="-707" frameWidth="1159" frameHeight="939"/>
	<SubTexture name="bf toy muerte0088" x="6639" y="1421" width="531" height="174" frameX="-474" frameY="-707" frameWidth="1159" frameHeight="939"/>
	<SubTexture name="bf toy muerte0089" x="6639" y="1421" width="531" height="174" frameX="-474" frameY="-707" frameWidth="1159" frameHeight="939"/>
	<SubTexture name="bf toy muerte0090" x="6639" y="1421" width="531" height="174" frameX="-474" frameY="-707" frameWidth="1159" frameHeight="939"/>
	<SubTexture name="bf toy muerte0091" x="6639" y="1421" width="531" height="174" frameX="-474" frameY="-707" frameWidth="1159" frameHeight="939"/>
	<SubTexture name="bf toy muerte0092" x="6639" y="1421" width="531" height="174" frameX="-474" frameY="-707" frameWidth="1159" frameHeight="939"/>
	<SubTexture name="bf toy muerte0093" x="6639" y="1421" width="531" height="174" frameX="-474" frameY="-707" frameWidth="1159" frameHeight="939"/>
	<SubTexture name="bf toy muerte0094" x="6639" y="1421" width="531" height="174" frameX="-474" frameY="-707" frameWidth="1159" frameHeight="939"/>
	<SubTexture name="bf toy muerte0095" x="6639" y="1421" width="531" height="174" frameX="-474" frameY="-707" frameWidth="1159" frameHeight="939"/>
	<SubTexture name="bf toy muerte0096" x="6639" y="1421" width="531" height="174" frameX="-474" frameY="-707" frameWidth="1159" frameHeight="939"/>
	<SubTexture name="bf toy muerte0097" x="6639" y="1421" width="531" height="174" frameX="-474" frameY="-707" frameWidth="1159" frameHeight="939"/>
	<SubTexture name="bf toy muerte0098" x="6639" y="1421" width="531" height="174" frameX="-474" frameY="-707" frameWidth="1159" frameHeight="939"/>
	<SubTexture name="bf toy muerte0099" x="6639" y="1421" width="531" height="174" frameX="-474" frameY="-707" frameWidth="1159" frameHeight="939"/>
	<SubTexture name="bf toy muerte0100" x="6639" y="1421" width="531" height="174" frameX="-474" frameY="-707" frameWidth="1159" frameHeight="939"/>
	<SubTexture name="bf toy muerte0101" x="6639" y="1421" width="531" height="174" frameX="-474" frameY="-707" frameWidth="1159" frameHeight="939"/>
	<SubTexture name="bf toy muerte0102" x="6639" y="1421" width="531" height="174" frameX="-474" frameY="-707" frameWidth="1159" frameHeight="939"/>
	<SubTexture name="bf toy muerte0103" x="6639" y="1421" width="531" height="174" frameX="-474" frameY="-707" frameWidth="1159" frameHeight="939"/>
	<SubTexture name="bf toy muerte0104" x="6639" y="1421" width="531" height="174" frameX="-474" frameY="-707" frameWidth="1159" frameHeight="939"/>
	<SubTexture name="bf toy muerte0105" x="6639" y="1421" width="531" height="174" frameX="-474" frameY="-707" frameWidth="1159" frameHeight="939"/>
	<SubTexture name="bf toy muerte0106" x="6639" y="1421" width="531" height="174" frameX="-474" frameY="-707" frameWidth="1159" frameHeight="939"/>
	<SubTexture name="bf toy muerte0107" x="6639" y="1421" width="531" height="174" frameX="-474" frameY="-707" frameWidth="1159" frameHeight="939"/>
	<SubTexture name="bf toy muerte0108" x="6639" y="1421" width="531" height="174" frameX="-474" frameY="-707" frameWidth="1159" frameHeight="939"/>
	<SubTexture name="bf toy muerte0109" x="6639" y="1421" width="531" height="174" frameX="-474" frameY="-707" frameWidth="1159" frameHeight="939"/>
	<SubTexture name="bf toy muerte0110" x="6639" y="1421" width="531" height="174" frameX="-474" frameY="-707" frameWidth="1159" frameHeight="939"/>
	<SubTexture name="bf toy muerte0111" x="6639" y="1421" width="531" height="174" frameX="-474" frameY="-707" frameWidth="1159" frameHeight="939"/>
	<SubTexture name="bf toy muerte0112" x="6639" y="1421" width="531" height="174" frameX="-474" frameY="-707" frameWidth="1159" frameHeight="939"/>
	<SubTexture name="bf toy muerte0113" x="6639" y="1421" width="531" height="174" frameX="-474" frameY="-707" frameWidth="1159" frameHeight="939"/>
	<SubTexture name="bf toy muerte0114" x="6639" y="1421" width="531" height="174" frameX="-474" frameY="-707" frameWidth="1159" frameHeight="939"/>
	<SubTexture name="bf toy muerte0115" x="6639" y="1421" width="531" height="174" frameX="-474" frameY="-707" frameWidth="1159" frameHeight="939"/>
	<SubTexture name="bf toy muerte0116" x="6639" y="1421" width="531" height="174" frameX="-474" frameY="-707" frameWidth="1159" frameHeight="939"/>
	<SubTexture name="bf toy muerte0117" x="6639" y="1421" width="531" height="174" frameX="-474" frameY="-707" frameWidth="1159" frameHeight="939"/>
	<SubTexture name="bf toy muerte0118" x="7197" y="1421" width="531" height="881" frameX="-474" frameY="0" frameWidth="1159" frameHeight="939"/>
	<SubTexture name="bf toy muerte0119" x="27" y="2329" width="531" height="782" frameX="-474" frameY="-99" frameWidth="1159" frameHeight="939"/>
	<SubTexture name="bf toy muerte0120" x="585" y="2329" width="552" height="210" frameX="-473" frameY="-666" frameWidth="1159" frameHeight="939"/>
	<SubTexture name="bf toy muerte0121" x="585" y="2329" width="552" height="210" frameX="-473" frameY="-666" frameWidth="1159" frameHeight="939"/>
	<SubTexture name="bf toy muerte0122" x="1164" y="2329" width="556" height="217" frameX="-469" frameY="-664" frameWidth="1159" frameHeight="939"/>
	<SubTexture name="bf toy muerte0123" x="1164" y="2329" width="556" height="217" frameX="-469" frameY="-664" frameWidth="1159" frameHeight="939"/>
	<SubTexture name="bf toy muerte0124" x="1164" y="2329" width="556" height="217" frameX="-469" frameY="-664" frameWidth="1159" frameHeight="939"/>
	<SubTexture name="bf toy muerte0125" x="1747" y="2329" width="556" height="216" frameX="-469" frameY="-665" frameWidth="1159" frameHeight="939"/>
	<SubTexture name="bf toy muerte0126" x="1747" y="2329" width="556" height="216" frameX="-469" frameY="-665" frameWidth="1159" frameHeight="939"/>
	<SubTexture name="bf toy muerte0127" x="2330" y="2329" width="579" height="196" frameX="-469" frameY="-688" frameWidth="1159" frameHeight="939"/>
	<SubTexture name="bf toy muerte0128" x="2330" y="2329" width="579" height="196" frameX="-469" frameY="-688" frameWidth="1159" frameHeight="939"/>
	<SubTexture name="bf toy muerte0129" x="2936" y="2329" width="580" height="193" frameX="-469" frameY="-688" frameWidth="1159" frameHeight="939"/>
	<SubTexture name="bf toy muerte0130" x="2936" y="2329" width="580" height="193" frameX="-469" frameY="-688" frameWidth="1159" frameHeight="939"/>
	<SubTexture name="bf toy muerte0131" x="2936" y="2329" width="580" height="193" frameX="-469" frameY="-688" frameWidth="1159" frameHeight="939"/>
	<SubTexture name="bf toy muerte0132" x="2936" y="2329" width="580" height="193" frameX="-469" frameY="-688" frameWidth="1159" frameHeight="939"/>
	<SubTexture name="bf toy muerte0133" x="3543" y="2329" width="580" height="193" frameX="-469" frameY="-688" frameWidth="1159" frameHeight="939"/>
	<SubTexture name="bf toy muerte0134" x="3543" y="2329" width="580" height="193" frameX="-469" frameY="-688" frameWidth="1159" frameHeight="939"/>
	<SubTexture name="bf toy muerte0135" x="3543" y="2329" width="580" height="193" frameX="-469" frameY="-688" frameWidth="1159" frameHeight="939"/>
	<SubTexture name="bf toy muerte0136" x="3543" y="2329" width="580" height="193" frameX="-469" frameY="-688" frameWidth="1159" frameHeight="939"/>
	<SubTexture name="bf toy muerte0137" x="3543" y="2329" width="580" height="193" frameX="-469" frameY="-688" frameWidth="1159" frameHeight="939"/>
	<SubTexture name="bf toy muerte0138" x="3543" y="2329" width="580" height="193" frameX="-469" frameY="-688" frameWidth="1159" frameHeight="939"/>
	<SubTexture name="bf toy muerte0139" x="3543" y="2329" width="580" height="193" frameX="-469" frameY="-688" frameWidth="1159" frameHeight="939"/>
	<SubTexture name="bf toy muerte0140" x="3543" y="2329" width="580" height="193" frameX="-469" frameY="-688" frameWidth="1159" frameHeight="939"/>
	<SubTexture name="bf toy muerte0141" x="3543" y="2329" width="580" height="193" frameX="-469" frameY="-688" frameWidth="1159" frameHeight="939"/>
	<SubTexture name="bf toy muerte0142" x="3543" y="2329" width="580" height="193" frameX="-469" frameY="-688" frameWidth="1159" frameHeight="939"/>
	<SubTexture name="bf toy muerte0143" x="3543" y="2329" width="580" height="193" frameX="-469" frameY="-688" frameWidth="1159" frameHeight="939"/>
	<SubTexture name="bf toy muerte0144" x="3543" y="2329" width="580" height="193" frameX="-469" frameY="-688" frameWidth="1159" frameHeight="939"/>
	<SubTexture name="bf toy muerte0145" x="3543" y="2329" width="580" height="193" frameX="-469" frameY="-688" frameWidth="1159" frameHeight="939"/>
	<SubTexture name="bf toy muerte0146" x="3543" y="2329" width="580" height="193" frameX="-469" frameY="-688" frameWidth="1159" frameHeight="939"/>
	<SubTexture name="bf toy muerte0147" x="3543" y="2329" width="580" height="193" frameX="-469" frameY="-688" frameWidth="1159" frameHeight="939"/>
	<SubTexture name="bf toy muerte0148" x="3543" y="2329" width="580" height="193" frameX="-469" frameY="-688" frameWidth="1159" frameHeight="939"/>
	<SubTexture name="bf toy muerte0149" x="4150" y="2329" width="690" height="334" frameX="-469" frameY="-547" frameWidth="1159" frameHeight="939"/>
	<SubTexture name="bf toy muerte0150" x="4150" y="2329" width="690" height="334" frameX="-469" frameY="-547" frameWidth="1159" frameHeight="939"/>
	<SubTexture name="bf toy muerte0151" x="4867" y="2329" width="690" height="334" frameX="-469" frameY="-547" frameWidth="1159" frameHeight="939"/>
	<SubTexture name="bf toy muerte0152" x="4867" y="2329" width="690" height="334" frameX="-469" frameY="-547" frameWidth="1159" frameHeight="939"/>
	<SubTexture name="bf toy muerte0153" x="4867" y="2329" width="690" height="334" frameX="-469" frameY="-547" frameWidth="1159" frameHeight="939"/>
	<SubTexture name="bf toy muerte enter o nose lol0000" x="5584" y="2329" width="690" height="334"/>
	<SubTexture name="bf toy muerte enter o nose lol0001" x="5584" y="2329" width="690" height="334"/>
	<SubTexture name="bf toy muerte enter o nose lol0002" x="6301" y="2329" width="690" height="334"/>
	<SubTexture name="bf toy muerte enter o nose lol0003" x="6301" y="2329" width="690" height="334"/>
	<SubTexture name="bf toy muerte enter o nose lol0004" x="7018" y="2329" width="690" height="334"/>
	<SubTexture name="bf toy muerte enter o nose lol0005" x="7018" y="2329" width="690" height="334"/>
	<SubTexture name="bf toy muerte enter o nose lol0006" x="27" y="3138" width="580" height="193" frameX="0" frameY="-141" frameWidth="690" frameHeight="334"/>
	<SubTexture name="bf toy muerte enter o nose lol0007" x="27" y="3138" width="580" height="193" frameX="0" frameY="-141" frameWidth="690" frameHeight="334"/>
	<SubTexture name="bf toy muerte enter o nose lol0008" x="27" y="3138" width="580" height="193" frameX="0" frameY="-141" frameWidth="690" frameHeight="334"/>
	<SubTexture name="bf toy muerte enter o nose lol0009" x="27" y="3138" width="580" height="193" frameX="0" frameY="-141" frameWidth="690" frameHeight="334"/>
	<SubTexture name="bf toy muerte enter o nose lol0010" x="27" y="3138" width="580" height="193" frameX="0" frameY="-141" frameWidth="690" frameHeight="334"/>
	<SubTexture name="bf toy muerte enter o nose lol0011" x="27" y="3138" width="580" height="193" frameX="0" frameY="-141" frameWidth="690" frameHeight="334"/>
	<SubTexture name="bf toy muerte enter o nose lol0012" x="27" y="3138" width="580" height="193" frameX="0" frameY="-141" frameWidth="690" frameHeight="334"/>
	<SubTexture name="bf toy muerte enter o nose lol0013" x="27" y="3138" width="580" height="193" frameX="0" frameY="-141" frameWidth="690" frameHeight="334"/>
	<SubTexture name="bf toy muerte enter o nose lol0014" x="27" y="3138" width="580" height="193" frameX="0" frameY="-141" frameWidth="690" frameHeight="334"/>
	<SubTexture name="bf toy muerte enter o nose lol0015" x="27" y="3138" width="580" height="193" frameX="0" frameY="-141" frameWidth="690" frameHeight="334"/>
	<SubTexture name="bf toy muerte enter o nose lol0016" x="27" y="3138" width="580" height="193" frameX="0" frameY="-141" frameWidth="690" frameHeight="334"/>
	<SubTexture name="bf toy muerte enter o nose lol0017" x="27" y="3138" width="580" height="193" frameX="0" frameY="-141" frameWidth="690" frameHeight="334"/>
	<SubTexture name="bf toy muerte enter o nose lol0018" x="27" y="3138" width="580" height="193" frameX="0" frameY="-141" frameWidth="690" frameHeight="334"/>
	<SubTexture name="bf toy muerte enter o nose lol0019" x="27" y="3138" width="580" height="193" frameX="0" frameY="-141" frameWidth="690" frameHeight="334"/>
	<SubTexture name="bf toy muerte enter o nose lol0020" x="27" y="3138" width="580" height="193" frameX="0" frameY="-141" frameWidth="690" frameHeight="334"/>
	<SubTexture name="bf toy muerte loop0000" x="634" y="3138" width="690" height="334"/>
	<SubTexture name="bf toy muerte loop0001" x="634" y="3138" width="690" height="334"/>
	<SubTexture name="bf toy muerte loop0002" x="1351" y="3138" width="690" height="334"/>
</TextureAtlas>
